celeste_anthropic/__init__.py
celeste_anthropic/py.typed
celeste_anthropic/messages/__init__.py
celeste_anthropic/messages/client.py
celeste_anthropic/messages/config.py
celeste_anthropic/messages/parameters.py
celeste_anthropic/messages/streaming.py
celeste_anthropic-0.3.6.dist-info/METADATA
celeste_anthropic-0.3.6.dist-info/WHEEL
celeste_anthropic-0.3.6.dist-info/RECORD
